aiocouchdb3/__init__.py
aiocouchdb3-0.1.5.dist-info/LICENSE
aiocouchdb3-0.1.5.dist-info/METADATA
aiocouchdb3-0.1.5.dist-info/WHEEL
aiocouchdb3-0.1.5.dist-info/RECORD
