Metadata-Version: 2.3
Name: aiocouchdb3
Version: 0.1.5
Summary: A client for interacting with CouchDB 3 based on aiohttp
License: The MIT License (MIT)
Author: Curtis Schlak
Author-email: 696163-realistschuckle@users.noreply.gitlab.com
Requires-Python: >=3.9
Classifier: License :: Other/Proprietary License
Classifier: Programming Language :: Python :: 3
Classifier: Programming Language :: Python :: 3.9
Classifier: Programming Language :: Python :: 3.10
Classifier: Programming Language :: Python :: 3.11
Classifier: Programming Language :: Python :: 3.12
Classifier: Programming Language :: Python :: 3.13
Provides-Extra: dev
Provides-Extra: test
Requires-Dist: aiohttp (>=3.11.18,<4.0.0)
Requires-Dist: neovim (>=0.3.1,<0.4.0) ; extra == "dev"
Requires-Dist: pyright (>=1.1.400,<2.0.0) ; extra == "dev"
Requires-Dist: pyright (>=1.1.400,<2.0.0) ; extra == "test"
Requires-Dist: pytest (>=8.3.5,<9.0.0) ; extra == "dev"
Requires-Dist: pytest (>=8.3.5,<9.0.0) ; extra == "test"
Requires-Dist: pytest-asyncio (>=0.26.0,<0.27.0) ; extra == "dev"
Requires-Dist: pytest-asyncio (>=0.26.0,<0.27.0) ; extra == "test"
Requires-Dist: pytest-cov (>=6.1.1,<7.0.0) ; extra == "dev"
Requires-Dist: pytest-cov (>=6.1.1,<7.0.0) ; extra == "test"
Requires-Dist: pytest-dotenv (>=0.5.2,<0.6.0) ; extra == "dev"
Requires-Dist: pytest-dotenv (>=0.5.2,<0.6.0) ; extra == "test"
Requires-Dist: pytest-watcher (>=0.4.3,<0.5.0) ; extra == "dev"
Requires-Dist: ruff (>=0.11.8,<0.12.0) ; extra == "dev"
Requires-Dist: ruff (>=0.11.8,<0.12.0) ; extra == "test"
